cdk_keycloak/__init__.py
cdk_keycloak/py.typed
cdk_keycloak/_jsii/__init__.py
cdk_keycloak/_jsii/cdk-keycloak@2.9.0.jsii.tgz
cdk_keycloak-2.9.0.dist-info/LICENSE
cdk_keycloak-2.9.0.dist-info/METADATA
cdk_keycloak-2.9.0.dist-info/NOTICE
cdk_keycloak-2.9.0.dist-info/WHEEL
cdk_keycloak-2.9.0.dist-info/top_level.txt
cdk_keycloak-2.9.0.dist-info/RECORD
